login_tracker/__init__.py
login_tracker/admin.py
login_tracker/apps.py
login_tracker/models.py
login_tracker/signals.py
login_tracker/tests.py
login_tracker/views.py
login_tracker/migrations/0001_initial.py
login_tracker/migrations/__init__.py
login_tracker-0.3.dist-info/LICENSE
login_tracker-0.3.dist-info/METADATA
login_tracker-0.3.dist-info/WHEEL
login_tracker-0.3.dist-info/top_level.txt
login_tracker-0.3.dist-info/RECORD
