Metadata-Version: 2.1
Name: login-tracker
Version: 0.3
Summary: A Django app to conduct Web-based login_tracker.
Home-page: https://github.com/doddahulugappa/login-tracker
Author: Doddahulugappa
Author-email: doddahulugappa@gmail.com
License: BSD-3-Clause
Project-URL: Bug Tracker, https://github.com/doddahulugappa/login-tracker/issues
Platform: UNKNOWN
Classifier: Environment :: Web Environment
Classifier: Framework :: Django
Classifier: Framework :: Django :: 2.1
Classifier: Intended Audience :: Developers
Classifier: License :: OSI Approved :: BSD License
Classifier: Operating System :: OS Independent
Classifier: Programming Language :: Python
Classifier: Programming Language :: Python :: 3
Classifier: Programming Language :: Python :: 3 :: Only
Classifier: Programming Language :: Python :: 3.6
Classifier: Programming Language :: Python :: 3.7
Classifier: Programming Language :: Python :: 3.8
Classifier: Topic :: Internet :: WWW/HTTP
Classifier: Topic :: Internet :: WWW/HTTP :: Dynamic Content
Requires-Python: >=3.6
License-File: LICENSE
Requires-Dist: Django (>=2.1)
